anysolve/__init__.py
anysolve-1.0.4.dist-info/LICENSE
anysolve-1.0.4.dist-info/METADATA
anysolve-1.0.4.dist-info/WHEEL
anysolve-1.0.4.dist-info/top_level.txt
anysolve-1.0.4.dist-info/RECORD
